recomp/rwlock/__init__.py
recomp/rwlock/rwlock.py
recomp_rwlock-0.1.dist-info/DESCRIPTION.rst
recomp_rwlock-0.1.dist-info/METADATA
recomp_rwlock-0.1.dist-info/RECORD
recomp_rwlock-0.1.dist-info/WHEEL
recomp_rwlock-0.1.dist-info/metadata.json
recomp_rwlock-0.1.dist-info/top_level.txt
recomp_rwlock-0.1.dist-info/zip-safe
